yaytarch/__init__.py
yaytarch/cli.py
yaytarch/clibp.py
yaytarch/db.py
yaytarch/schema.sql
yaytarch/videocollections.py
yaytarch/videos.py
yaytarch/model/__init__.py
yaytarch/model/db/__init__.py
yaytarch/model/db/collectionmodel.py
yaytarch/model/db/configurationmodel.py
yaytarch/model/db/videocollectionrelmodel.py
yaytarch/model/db/videomodel.py
yaytarch/model/file/__init__.py
yaytarch/model/file/jsonconfigmodel.py
yaytarch/model/file/jsonvideomodel.py
yaytarch/static/bg.png
yaytarch/static/imagenotfound.png
yaytarch/static/style.css
yaytarch/templates/base.html
yaytarch/templates/collections.html
yaytarch/templates/localvideolist.html
yaytarch/templates/localvideoplay.html
yaytarch/templates/videolist.html
yaytarch/templates/videoplay.html
yaytarch/tools/__init__.py
yaytarch/tools/backup.py
yaytarch/tools/config.py
yaytarch/tools/outputformat.py
yaytarch/tools/urltools.py
yaytarch/tools/videodownload.py
yaytarch-1.1.0.dist-info/LICENSE
yaytarch-1.1.0.dist-info/METADATA
yaytarch-1.1.0.dist-info/WHEEL
yaytarch-1.1.0.dist-info/entry_points.txt
yaytarch-1.1.0.dist-info/top_level.txt
yaytarch-1.1.0.dist-info/RECORD
