Metadata-Version: 2.1
Name: yaytarch
Version: 1.1.0
Summary: light yt-dlp frontend
Author-email: "Paolo D." <pawel.dunskimoc@gmail.com>
Project-URL: Homepage, https://github.com/absolutelyrelative/yaytarch
Requires-Python: >=3.7
License-File: LICENSE
Requires-Dist: flask
Requires-Dist: yt-dlp
